unicodex/__init__.py
unicodex/__main__.py
unicodex-6.6.6.dist-info/LICENSE
unicodex-6.6.6.dist-info/METADATA
unicodex-6.6.6.dist-info/WHEEL
unicodex-6.6.6.dist-info/top_level.txt
unicodex-6.6.6.dist-info/RECORD
