Metadata-Version: 2.1
Name: unicodex
Version: 6.6.6
Summary: Unicodes encoder, decoder & converter
Home-page: https://github.com/llawllet
Author: odi
Author-email: ivuxey@gmail.com
License: MIT
Project-URL: Bug Tracker, https://github.com/llawllet
Keywords: unicode,converter,unicodex
Classifier: Programming Language :: Python :: 3
Classifier: License :: OSI Approved :: MIT License
Classifier: Operating System :: OS Independent
Requires-Python: >=3.8
License-File: LICENSE
